django_secux/__init__.py
django_secux/apps.py
django_secux/captcha.py
django_secux/decorator.py
django_secux/middleware.py
django_secux/models.py
django_secux/signals.py
django_secux/tools.py
django_secux/user.py
django_secux/views.py
django_secux/migrations/__init__.py
django_secux/templatetags/__init__.py
django_secux/templatetags/secux_captcha.py
django_secux-6.0.0.dist-info/licenses/LICENSE
django_secux-6.0.0.dist-info/METADATA
django_secux-6.0.0.dist-info/WHEEL
django_secux-6.0.0.dist-info/top_level.txt
django_secux-6.0.0.dist-info/RECORD
