Metadata-Version: 2.4
Name: django-secux
Version: 6.0.0
Summary: All-in-One Django Security & Optimization
Home-page: https://github.com/xo-aria/django-secux
Author: XO Aria
Author-email: XO Aria <hf18950@gmail.com>
License: MIT
Project-URL: Homepage, https://github.com/xo-aria/django-secux
Project-URL: Repository, https://github.com/xo-aria/django-secux
Project-URL: Issues, https://github.com/xo-aria/django-secux/issues
Classifier: Framework :: Django
Classifier: Framework :: Django :: 4.2
Classifier: Intended Audience :: Developers
Classifier: License :: OSI Approved :: MIT License
Classifier: Programming Language :: Python :: 3
Classifier: Programming Language :: Python :: 3.8
Classifier: Programming Language :: Python :: 3.9
Classifier: Programming Language :: Python :: 3.10
Classifier: Operating System :: OS Independent
Requires-Python: >=3.8
License-File: LICENSE
Requires-Dist: Django>=4.2
Requires-Dist: Pillow>=9.0.0
Dynamic: author
Dynamic: home-page
Dynamic: license-file
